{"type":"PR","pr":{"number":240,"head":"8dfa273794595e3a8f1b6fa123113a23e19418c9"},"user":"kamran","status":"pending_publish","branch":"cms/-interview-nakadia-welove","collection":"interviews","title":"Nakadia @ WeLove","description":"We spoke to the talented Nakadia about her global success, work ethic and friendship with a certain Mr Sven Vath.","objects":{"entry":{"path":"src/pages/interviews/-interview-nakadia-welove.md","sha":"a3b2ee26aea7c032c3d1f3a820fc0669786784d6"},"files":[]},"timeStamp":"2018-05-20T15:05:31.240Z"}